cfaudit/__init__.py
cfaudit/aws/__init__.py
cfaudit/aws/analysis.py
cfaudit/aws/attached.py
cfaudit/aws/authentication.py
cfaudit/aws/exceptions.py
cfaudit/aws/output.py
cfaudit/aws/whitelist.py
cfaudit/cli/__init__.py
cfaudit/cli/aws.py
cfaudit/generic/__init__.py
cfaudit/generic/helpers.py
cfaudit/generic/output.py
cfaudit/sg_audit.py
cfaudit-0.4.dist-info/entry_points.txt
cfaudit-0.4.dist-info/WHEEL
cfaudit-0.4.dist-info/METADATA
cfaudit-0.4.dist-info/RECORD
