Metadata-Version: 2.1
Name: cfaudit
Version: 0.4
Summary: The CityFibre AWS security group analyzer
License: Apache-2.0
Keywords: cfaudit,aws,security,analysis
Author: Sergii Reznichenko
Author-email: srezni@softserveinc.com
Requires-Python: >=3.7,<4.0
Classifier: License :: OSI Approved :: Apache Software License
Classifier: Programming Language :: Python :: 3
Classifier: Programming Language :: Python :: 3.10
Classifier: Programming Language :: Python :: 3.7
Classifier: Programming Language :: Python :: 3.8
Classifier: Programming Language :: Python :: 3.9
Requires-Dist: Jinja2 (>=2.11,<3.0)
Requires-Dist: PyYAML (>=5.3,<6.0)
Requires-Dist: boto3 (>=1.14,<2.0)
Requires-Dist: click (>=7.1,<8.0)
Requires-Dist: colorama (>=0.4.3,<0.5.0)
